crossywords/__init__.py
crossywords/algorithm.py
crossywords/main.py
crossywords-0.0.6.dist-info/LICENSE
crossywords-0.0.6.dist-info/METADATA
crossywords-0.0.6.dist-info/WHEEL
crossywords-0.0.6.dist-info/top_level.txt
crossywords-0.0.6.dist-info/RECORD
