Metadata-Version: 2.1
Name: crossywords
Version: 0.0.6
Summary: Word matrix generator that creates the word matrix in a way to have multiple words in one 5x5 matrix.
Home-page: https://github.com/AndreyVolkovBI/CrossyWords
Author: Andrey Volkov
Author-email: andrey@volkov.tech
License: UNKNOWN
Platform: UNKNOWN
Classifier: Programming Language :: Python :: 3
Classifier: License :: OSI Approved :: MIT License
Classifier: Operating System :: OS Independent
